{
  "IsRegenerate": true,
  "MenuPosition": "main",
  "RelativeNamespace": "Shop",
  "EntityName": "ProductCustomerStat",
  "EntityNamePlural": "ProductCustomerStats",
  "TableName": "ProductCustomerStats",
  "PrimaryKeyType": "long",
  "BaseClass": "CreationAuditedEntity",
  "EntityHistory": false,
  "AutoMigration": true,
  "UpdateDatabase": true,
  "CreateUserInterface": true,
  "CreateViewOnly": true,
  "CreateExcelExport": true,
  "IsNonModalCRUDPage": false,
  "IsMasterDetailPage": false,
  "PagePermission": {
    "Host": true,
    "Tenant": true
  },
  "Properties": [
    {
      "Name": "Clicked",
      "Type": "bool",
      "MaxLength": -1,
      "MinLength": -1,
      "Range": {
        "IsRangeSet": false,
        "MinimumValue": 0.0,
        "MaximumValue": 0.0
      },
      "Required": false,
      "Nullable": false,
      "Regex": "",
      "UserInterface": {
        "AdvancedFilter": true,
        "List": true,
        "CreateOrUpdate": true
      },
      "ViewType": null,
      "AdditionalData": {}
    },
    {
      "Name": "WishedOrFavorite",
      "Type": "bool",
      "MaxLength": -1,
      "MinLength": -1,
      "Range": {
        "IsRangeSet": false,
        "MinimumValue": 0.0,
        "MaximumValue": 0.0
      },
      "Required": false,
      "Nullable": false,
      "Regex": "",
      "UserInterface": {
        "AdvancedFilter": true,
        "List": true,
        "CreateOrUpdate": true
      },
      "ViewType": null,
      "AdditionalData": {}
    },
    {
      "Name": "Purchased",
      "Type": "bool",
      "MaxLength": -1,
      "MinLength": -1,
      "Range": {
        "IsRangeSet": false,
        "MinimumValue": 0.0,
        "MaximumValue": 0.0
      },
      "Required": false,
      "Nullable": false,
      "Regex": "",
      "UserInterface": {
        "AdvancedFilter": true,
        "List": true,
        "CreateOrUpdate": true
      },
      "ViewType": null,
      "AdditionalData": {}
    },
    {
      "Name": "PurchasedQuantity",
      "Type": "int",
      "MaxLength": -1,
      "MinLength": -1,
      "Range": {
        "IsRangeSet": false,
        "MinimumValue": 0.0,
        "MaximumValue": 0.0
      },
      "Required": false,
      "Nullable": true,
      "Regex": "",
      "UserInterface": {
        "AdvancedFilter": true,
        "List": true,
        "CreateOrUpdate": true
      },
      "ViewType": null,
      "AdditionalData": {}
    },
    {
      "Name": "Shared",
      "Type": "bool",
      "MaxLength": -1,
      "MinLength": -1,
      "Range": {
        "IsRangeSet": false,
        "MinimumValue": 0.0,
        "MaximumValue": 0.0
      },
      "Required": false,
      "Nullable": false,
      "Regex": "",
      "UserInterface": {
        "AdvancedFilter": true,
        "List": true,
        "CreateOrUpdate": true
      },
      "ViewType": null,
      "AdditionalData": {}
    },
    {
      "Name": "PageLink",
      "Type": "string",
      "MaxLength": -1,
      "MinLength": -1,
      "Range": {
        "IsRangeSet": false,
        "MinimumValue": 0.0,
        "MaximumValue": 0.0
      },
      "Required": false,
      "Nullable": false,
      "Regex": "",
      "UserInterface": {
        "AdvancedFilter": true,
        "List": true,
        "CreateOrUpdate": true
      },
      "ViewType": null,
      "AdditionalData": {}
    },
    {
      "Name": "AppOrWeb",
      "Type": "bool",
      "MaxLength": -1,
      "MinLength": -1,
      "Range": {
        "IsRangeSet": false,
        "MinimumValue": 0.0,
        "MaximumValue": 0.0
      },
      "Required": false,
      "Nullable": false,
      "Regex": "",
      "UserInterface": {
        "AdvancedFilter": true,
        "List": true,
        "CreateOrUpdate": true
      },
      "ViewType": null,
      "AdditionalData": {}
    },
    {
      "Name": "QuitFromLink",
      "Type": "string",
      "MaxLength": -1,
      "MinLength": -1,
      "Range": {
        "IsRangeSet": false,
        "MinimumValue": 0.0,
        "MaximumValue": 0.0
      },
      "Required": false,
      "Nullable": false,
      "Regex": "",
      "UserInterface": {
        "AdvancedFilter": true,
        "List": true,
        "CreateOrUpdate": true
      },
      "ViewType": null,
      "AdditionalData": {}
    }
  ],
  "NavigationProperties": [
    {
      "Namespace": "SoftGrid.Shop",
      "ForeignEntityName": "Product",
      "IdType": "long",
      "IsNullable": true,
      "PropertyName": "ProductId",
      "DuplicationNumber": 0,
      "RelationType": "single",
      "ViewType": "LookupTable",
      "DisplayPropertyNameInfos": {
        "MergeFormat": "{0}",
        "DisplayPropertyNames": [
          "Name"
        ]
      }
    },
    {
      "Namespace": "SoftGrid.CRM",
      "ForeignEntityName": "Contact",
      "IdType": "long",
      "IsNullable": true,
      "PropertyName": "ContactId",
      "DuplicationNumber": 0,
      "RelationType": "single",
      "ViewType": "LookupTable",
      "DisplayPropertyNameInfos": {
        "MergeFormat": "{0}",
        "DisplayPropertyNames": [
          "FullName"
        ]
      }
    },
    {
      "Namespace": "SoftGrid.Shop",
      "ForeignEntityName": "Store",
      "IdType": "long",
      "IsNullable": true,
      "PropertyName": "StoreId",
      "DuplicationNumber": 0,
      "RelationType": "single",
      "ViewType": "LookupTable",
      "DisplayPropertyNameInfos": {
        "MergeFormat": "{0}",
        "DisplayPropertyNames": [
          "Name"
        ]
      }
    },
    {
      "Namespace": "SoftGrid.Territory",
      "ForeignEntityName": "Hub",
      "IdType": "long",
      "IsNullable": true,
      "PropertyName": "HubId",
      "DuplicationNumber": 0,
      "RelationType": "single",
      "ViewType": "LookupTable",
      "DisplayPropertyNameInfos": {
        "MergeFormat": "{0}",
        "DisplayPropertyNames": [
          "Name"
        ]
      }
    },
    {
      "Namespace": "SoftGrid.LookupData",
      "ForeignEntityName": "SocialMedia",
      "IdType": "long",
      "IsNullable": true,
      "PropertyName": "SocialMediaId",
      "DuplicationNumber": 0,
      "RelationType": "single",
      "ViewType": "LookupTable",
      "DisplayPropertyNameInfos": {
        "MergeFormat": "{0}",
        "DisplayPropertyNames": [
          "Name"
        ]
      }
    }
  ],
  "NavigationPropertyOneToManyTables": [],
  "EnumDefinitions": [],
  "DbContext": null
}